miqro_alarm/__init__.py
miqro_alarm/alarm.py
miqro_alarm-0.3.0.dist-info/METADATA
miqro_alarm-0.3.0.dist-info/WHEEL
miqro_alarm-0.3.0.dist-info/entry_points.txt
miqro_alarm-0.3.0.dist-info/licenses/LICENSE
miqro_alarm-0.3.0.dist-info/RECORD
